easysubmit/__init__.py
easysubmit/base.py
easysubmit/config.py
easysubmit/entities.py
easysubmit/functions.py
easysubmit/helpers.py
easysubmit/profiler.py
easysubmit/slurm.py
easysubmit-0.3.1.dist-info/METADATA
easysubmit-0.3.1.dist-info/WHEEL
easysubmit-0.3.1.dist-info/licenses/LICENSE
easysubmit-0.3.1.dist-info/RECORD
