Metadata-Version: 2.4
Name: easysubmit
Version: 0.3.1
Summary: A Python library for simplified job scheduling and management on SLURM clusters
Project-URL: Documentation, https://github.com/ysenarath/easysubmit#readme
Project-URL: Issues, https://github.com/ysenarath/easysubmit/issues
Project-URL: Source, https://github.com/ysenarath/easysubmit
Author-email: Yasas Senarath <12231659+ysenarath@users.noreply.github.com>
License-Expression: MIT
License-File: LICENSE
Keywords: batch-processing,cluster-computing,distributed-computing,hpc,job-scheduling,parallel-computing,scientific-computing,slurm,task-management,workflow
Classifier: Development Status :: 4 - Beta
Classifier: Programming Language :: Python
Classifier: Programming Language :: Python :: 3.9
Classifier: Programming Language :: Python :: 3.10
Classifier: Programming Language :: Python :: 3.11
Classifier: Programming Language :: Python :: 3.12
Classifier: Programming Language :: Python :: Implementation :: CPython
Classifier: Programming Language :: Python :: Implementation :: PyPy
Requires-Python: >=3.9
Requires-Dist: cloudpickle>=3.1.1
Requires-Dist: nightjar>=0.0.5
Requires-Dist: typing-extensions>=4.12.2
Provides-Extra: scalene
Requires-Dist: scalene>=1.5.51; extra == 'scalene'
